pocx/__init__.py
pocx/aio_poc.py
pocx/basic_poc.py
pocx/funcs/__init__.py
pocx/funcs/ceye.py
pocx/funcs/fofa.py
pocx/funcs/snow_flake.py
pocx-0.2.3.dist-info/LICENSE
pocx-0.2.3.dist-info/METADATA
pocx-0.2.3.dist-info/WHEEL
pocx-0.2.3.dist-info/RECORD
